GetLatestGamePrices/ExtractPriceData.py
GetLatestGamePrices/__init__.py
getlatestgameprices-0.2.0.dist-info/licenses/LICENSE
getlatestgameprices-0.2.0.dist-info/METADATA
getlatestgameprices-0.2.0.dist-info/WHEEL
getlatestgameprices-0.2.0.dist-info/top_level.txt
getlatestgameprices-0.2.0.dist-info/RECORD
