Metadata-Version: 2.4
Name: GetLatestGamePrices
Version: 0.2.0
Summary: This Package gets you the deals about a single game from ggdeals. also this is my first package to learn about things like packages, version control, github actions
Home-page: https://github.com/Abhay_Cerberus/GetLatestGamePrices
Author: AbhayCerberus
Author-email: mistercerberus01+pypiPackage@gmail.com
License-File: LICENSE
Requires-Dist: requests
Requires-Dist: beautifulsoup4
Dynamic: author
Dynamic: author-email
Dynamic: home-page
Dynamic: license-file
Dynamic: requires-dist
Dynamic: summary
